MOJIZA/__init__.py
MOJIZA/runer.py
MOJIZA/version.py
MOJIZA/engine/__init__.py
MOJIZA/engine/p_gen.py
MOJIZA/engine/routing.py
MOJIZA/engine/server.py
MOJIZA/models/__init__.py
MOJIZA/models/base.py
MOJIZA/static/__init__.py
MOJIZA/static/make_static.py
mojiza-0.1.3.dist-info/licenses/LICENSE
mojiza-0.1.3.dist-info/METADATA
mojiza-0.1.3.dist-info/WHEEL
mojiza-0.1.3.dist-info/top_level.txt
mojiza-0.1.3.dist-info/RECORD
