Metadata-Version: 2.4
Name: mojiza
Version: 0.1.3
Summary: A lightweight Python web framework
Author-email: Abdulhodiy <muhiddinovabdulhodiy2@gmail.com>
License: GPL-3.0-only
Classifier: Development Status :: 4 - Beta
Classifier: Intended Audience :: Developers
Classifier: Programming Language :: Python :: 3
Classifier: License :: OSI Approved :: GNU General Public License v3 (GPLv3)
Classifier: Operating System :: OS Independent
Requires-Python: >=3.6
License-File: LICENSE
Requires-Dist: aiosqlite
Requires-Dist: Jinja2>=3.1.4
Requires-Dist: loguru>=0.7.3
Requires-Dist: watchdog>=6.0.0
Requires-Dist: aiohttp>=3.11.10
Requires-Dist: qrcode>=8.0
Dynamic: license-file
Dynamic: requires-python
